{
  "indexes": [
    {
      "collectionGroup": "partnerStatements",
      "queryScope": "COLLECTION",
      "fields": [
        { "fieldPath": "partnerId", "order": "ASCENDING" },
        { "fieldPath": "generatedAt", "order": "DESCENDING" }
      ]
    },
    {
      "collectionGroup": "threads",
      "queryScope": "COLLECTION",
      "fields": [
        { "fieldPath": "participants", "arrayConfig": "CONTAINS" },
        { "fieldPath": "lastMessageAt", "order": "DESCENDING" }
      ]
    },
    {
      "collectionGroup": "bot_sessions",
      "queryScope": "COLLECTION",
      "fields": [
        { "fieldPath": "tenantId", "order": "ASCENDING" },
        { "fieldPath": "updatedAt", "order": "DESCENDING" }
      ]
    },
    {
      "collectionGroup": "partnerInvoices",
      "queryScope": "COLLECTION",
      "fields": [
        { "fieldPath": "partnerId", "order": "ASCENDING" },
        { "fieldPath": "issueDate", "order": "DESCENDING" }
      ]
    },
    {
      "collectionGroup": "posts",
      "queryScope": "COLLECTION",
      "fields": [
        { "fieldPath": "status", "order": "ASCENDING" },
        { "fieldPath": "publishedAt", "order": "DESCENDING" }
      ]
    },
    {
      "collectionGroup": "reports",
      "queryScope": "COLLECTION",
      "fields": [
        { "fieldPath": "status", "order": "ASCENDING" },
        { "fieldPath": "supervisorId", "order": "ASCENDING" },
        { "fieldPath": "updatedAt", "order": "DESCENDING" }
      ]
    },
    {
      "collectionGroup": "reports",
      "queryScope": "COLLECTION",
      "fields": [
        { "fieldPath": "tenantId", "order": "ASCENDING" },
        { "fieldPath": "createdAt", "order": "DESCENDING" }
      ]
    },
    {
      "collectionGroup": "consultation_sessions",
      "queryScope": "COLLECTION",
      "fields": [
        { "fieldPath": "practitionerId", "order": "ASCENDING" },
        { "fieldPath": "scheduledAt", "order": "DESCENDING" }
      ]
    },
    {
      "collectionGroup": "consultation_sessions",
      "queryScope": "COLLECTION",
      "fields": [
        { "fieldPath": "tenantId", "order": "ASCENDING" },
        { "fieldPath": "createdAt", "order": "DESCENDING" }
      ]
    },
    {
      "collectionGroup": "integrations",
      "queryScope": "COLLECTION",
      "fields": [
        { "fieldPath": "tenantId", "order": "ASCENDING" },
        { "fieldPath": "updatedAt", "order": "DESCENDING" }
      ]
    },
    {
      "collectionGroup": "cases",
      "queryScope": "COLLECTION",
      "fields": [
        { "fieldPath": "tenantId", "order": "ASCENDING" },
        { "fieldPath": "createdAt", "order": "DESCENDING" }
      ]
    },
    {
      "collectionGroup": "cases",
      "queryScope": "COLLECTION",
      "fields": [
        { "fieldPath": "tenantId", "order": "ASCENDING" },
        { "fieldPath": "updatedAt", "order": "DESCENDING" }
      ]
    },
    {
      "collectionGroup": "students",
      "queryScope": "COLLECTION",
      "fields": [
        { "fieldPath": "tenantId", "order": "ASCENDING" },
        { "fieldPath": "createdAt", "order": "DESCENDING" }
      ]
    },
    {
      "collectionGroup": "schools",
      "queryScope": "COLLECTION",
      "fields": [
        { "fieldPath": "tenantId", "order": "ASCENDING" },
        { "fieldPath": "createdAt", "order": "DESCENDING" }
      ]
    },
    {
      "collectionGroup": "appointments",
      "queryScope": "COLLECTION",
      "fields": [
        { "fieldPath": "tenantId", "order": "ASCENDING" },
        { "fieldPath": "createdAt", "order": "DESCENDING" }
      ]
    },
    {
      "collectionGroup": "trainingModules",
      "queryScope": "COLLECTION",
      "fields": [
        { "fieldPath": "tenantId", "order": "ASCENDING" },
        { "fieldPath": "createdAt", "order": "DESCENDING" }
      ]
    },
    {
      "collectionGroup": "assessment_assignments",
      "queryScope": "COLLECTION",
      "fields": [
        { "fieldPath": "tenantId", "order": "ASCENDING" },
        { "fieldPath": "createdAt", "order": "DESCENDING" }
      ]
    },
    {
      "collectionGroup": "assessment_results",
      "queryScope": "COLLECTION",
      "fields": [
        { "fieldPath": "tenantId", "order": "ASCENDING" },
        { "fieldPath": "createdAt", "order": "DESCENDING" }
      ]
    },
    {
      "collectionGroup": "observations",
      "queryScope": "COLLECTION",
      "fields": [
        { "fieldPath": "tenantId", "order": "ASCENDING" },
        { "fieldPath": "createdAt", "order": "DESCENDING" }
      ]
    },
    {
      "collectionGroup": "certificates",
      "queryScope": "COLLECTION",
      "fields": [
        { "fieldPath": "tenantId", "order": "ASCENDING" },
        { "fieldPath": "issuedAt", "order": "DESCENDING" }
      ]
    }
  ],
  "fieldOverrides": []
}
